[
    {
        "id": 1,
        "userId": 1,
        "title": "yaxshi video",
        "file": "12344.video.mp4",
        "date": "2024/16/04",
        "size": "20mb"
    },
    {
        "id": 2,
        "userId": "2",
        "title": "Panda kunfu",
        "file": "1713260939567.video.mp4",
        "size": 0.18592166900634766,
        "date": "2024-04-16T09:48:59.568Z"
    },
    {
        "id": 3,
        "userId": "3",
        "title": "Panda",
        "file": "1713262572080.video.mp4",
        "size": 0.18592166900634766,
        "date": "2024-04-16T10:16:12.080Z"
    }
]